jan883_codebase/__init__.py
jan883_codebase/main.py
jan883_codebase/NER/ner.py
jan883_codebase/automation/__init__.py
jan883_codebase/automation/automation_scheduler.py
jan883_codebase/automation/browser_shotcut.py
jan883_codebase/automation/daily_scheduler.py
jan883_codebase/automation/icloud_email.py
jan883_codebase/automation/image_renamer.py
jan883_codebase/automation/news_automation.py
jan883_codebase/automation/organize_files.py
jan883_codebase/automation/search good first issues.py
jan883_codebase/automation/trending_repos.py
jan883_codebase/automation/weather_forcast.py
jan883_codebase/csv_to_database/__init__.py
jan883_codebase/csv_to_database/csv_import_functions.py
jan883_codebase/csv_to_database/data.csv
jan883_codebase/csv_to_database/main.ipynb
jan883_codebase/csv_to_database/datasets/data.csv
jan883_codebase/csv_to_database/datasets/sepsis_train.csv
jan883_codebase/csv_to_database/datasets/test.csv
jan883_codebase/csv_to_database/datasets/train.csv
jan883_codebase/data_loading/__init__.py
jan883_codebase/data_loading/csv.py
jan883_codebase/data_preprocessing/__init__.py
jan883_codebase/data_preprocessing/eda.py
jan883_codebase/data_preprocessing/model_selection.py
jan883_codebase/git_automation/__init__.py
jan883_codebase/git_automation/git_merge.py
jan883_codebase/git_automation/git_push.py
jan883_codebase/google_sheets/__init__.py
jan883_codebase/google_sheets/sheethelper.py
jan883_codebase/llm/__init__.py
jan883_codebase/llm/groq.py
jan883_codebase/llm/new.py
jan883_codebase/llm/ollama.py
jan883_codebase/llm/perplexity.py
jan883_codebase/llm/utils.py
jan883_codebase/llm_agents/__init__.py
jan883_codebase/llm_agents/crewai_policy.py
jan883_codebase/llm_agents/crewai_websearch.py
jan883_codebase/llm_agents/select_model.py
jan883_codebase/machine_learning/__init__.py
jan883_codebase/machine_learning/kan.py
jan883_codebase/machine_learning/model_selection.py
jan883_codebase/notion_api/__init__.py
jan883_codebase/notion_api/notionhelper.py
jan883_codebase-0.2.0.dist-info/METADATA
jan883_codebase-0.2.0.dist-info/WHEEL
jan883_codebase-0.2.0.dist-info/entry_points.txt
jan883_codebase-0.2.0.dist-info/licenses/LICENSE
jan883_codebase-0.2.0.dist-info/RECORD
