Metadata-Version: 2.4
Name: jan883_codebase
Version: 0.2.0
Summary: Personal codebase for data science and machine learning projects. Includes data preprocessing, feature engineering, model selection, and model evaluation.
Project-URL: Homepage, https://github.com/janduplessis883/jan883-codebase
Project-URL: Documentation, https://github.com/janduplessis883/jan883-codebase#readme
Project-URL: Repository, https://github.com/janduplessis883/jan883-codebase
Project-URL: Issues, https://github.com/janduplessis883/jan883-codebase/issues
Project-URL: Changelog, https://github.com/janduplessis883/jan883-codebase/blob/main/CHANGELOG.md
Author-email: Jan du Plessis <drjanduplessis@icloud.com>
License: MIT License
License-File: LICENSE
Keywords: EDA,data science,machine learning,modeling,utilities
Classifier: Development Status :: 3 - Alpha
Classifier: Intended Audience :: Developers
Classifier: Intended Audience :: Science/Research
Classifier: License :: OSI Approved :: MIT License
Classifier: Programming Language :: Python :: 3
Classifier: Programming Language :: Python :: 3.8
Classifier: Programming Language :: Python :: 3.9
Classifier: Programming Language :: Python :: 3.10
Classifier: Programming Language :: Python :: 3.11
Classifier: Programming Language :: Python :: 3.12
Classifier: Topic :: Scientific/Engineering :: Information Analysis
Classifier: Topic :: Software Development :: Libraries :: Python Modules
Requires-Python: >=3.8
Requires-Dist: click
Requires-Dist: colorama
Requires-Dist: crewai
Requires-Dist: imbalanced-learn
Requires-Dist: ipython
Requires-Dist: joblib
Requires-Dist: loguru
Requires-Dist: matplotlib
Requires-Dist: notion-client
Requires-Dist: numpy
Requires-Dist: pandas
Requires-Dist: requests
Requires-Dist: scikit-learn
Requires-Dist: scipy
Requires-Dist: seaborn
Requires-Dist: statsmodels
Requires-Dist: tqdm
Requires-Dist: xgboost
Requires-Dist: yellowbrick
Provides-Extra: dev
Requires-Dist: black>=22.0.0; extra == 'dev'
Requires-Dist: flake8>=4.0.0; extra == 'dev'
Requires-Dist: mypy>=0.900; extra == 'dev'
Requires-Dist: pytest>=6.0.0; extra == 'dev'
